README.md
setup.py
src/airobots/__init__.py
src/airobots/__main__.py
src/airobots.egg-info/PKG-INFO
src/airobots.egg-info/SOURCES.txt
src/airobots.egg-info/dependency_links.txt
src/airobots.egg-info/entry_points.txt
src/airobots.egg-info/requires.txt
src/airobots.egg-info/top_level.txt
src/airobots/core/__init__.py
src/airobots/core/api.py
src/airobots/core/settings.py
src/airobots/poco/__init__.py
src/airobots/poco/android.py
src/airobots/poco/ios.py
src/airobots/robot/__init__.py