Metadata-Version: 2.1
Name: airobots
Version: 1.2.1
Summary: UI Test Automation Framework for Games and Apps on Android/iOS/Windows/Linux/Web
Home-page: https://github.com/BSTester/Airobots
Author: 贝克街的捉虫师
Author-email: forpeng@foxmail.com
License: Apache License 2.0
Project-URL: Source, https://github.com/BSTester/Airobots
Keywords: automation,automated-test,game,android,ios,windows,linux,web
Platform: UNKNOWN
Classifier: Development Status :: 4 - Beta
Classifier: Intended Audience :: Developers
Classifier: Topic :: Software Development :: Build Tools
Classifier: License :: OSI Approved :: MIT License
Classifier: Programming Language :: Python :: 3.6
Classifier: Programming Language :: Python :: 3.7
Classifier: Programming Language :: Python :: 3.8
Classifier: Programming Language :: Python :: 3.9
Classifier: Programming Language :: Python :: 3 :: Only
Requires-Python: >=3.5, <4
